[
  {
    "index": 6,
    "text": "마이페이지",
    "href": "/mypage/memberManage.do?upperMenuId=14000000&menuNo=14500000",
    "onclick": "",
    "target": "",
    "has_bbs_id": false,
    "outer_html": "<a class=\"my\" href=\"/mypage/memberManage.do?upperMenuId=14000000&amp;menuNo=14500000\">마이페이지</a>"
  },
  {
    "index": 9,
    "text": "지방세 관계 법령",
    "href": "/ordinance/importantList.do?menuNo=80100100&upperMenuId=8010000",
    "onclick": "",
    "target": "",
    "has_bbs_id": false,
    "outer_html": "<a href=\"/ordinance/importantList.do?menuNo=80100100&amp;upperMenuId=8010000\">지방세 관계 법령</a>"
  },
  {
    "index": 10,
    "text": "지방자치단체 조례",
    "href": "/ordinance/rulesListAPI.do?menuNo=8020000&upperMenuId=8000000",
    "onclick": "",
    "target": "",
    "has_bbs_id": false,
    "outer_html": "<a href=\"/ordinance/rulesListAPI.do?menuNo=8020000&amp;upperMenuId=8000000\">지방자치단체 조례</a>"
  },
  {
    "index": 11,
    "text": "최신 개정법령",
    "href": "/ordinance/theLastestList.do?menuNo=8030000&upperMenuId=8000000",
    "onclick": "",
    "target": "",
    "has_bbs_id": false,
    "outer_html": "<a href=\"/ordinance/theLastestList.do?menuNo=8030000&amp;upperMenuId=8000000\">최신 개정법령</a>"
  },
  {
    "index": 12,
    "text": "판례와 해석",
    "href": "/explainInfo/constitutionDcnList.do?menuNo=9060000&upperMenuId=9000000",
    "onclick": "",
    "target": "",
    "has_bbs_id": false,
    "outer_html": "<a href=\"/explainInfo/constitutionDcnList.do?menuNo=9060000&amp;upperMenuId=9000000\" class=\"\">판례와 해석</a>"
  },
  {
    "index": 13,
    "text": "헌법재판소 결정례",
    "href": "/explainInfo/constitutionDcnList.do?menuNo=9060000&upperMenuId=9000000",
    "onclick": "",
    "target": "",
    "has_bbs_id": false,
    "outer_html": "<a href=\"/explainInfo/constitutionDcnList.do?menuNo=9060000&amp;upperMenuId=9000000\">헌법재판소 결정례</a>"
  },
  {
    "index": 14,
    "text": "법원 판례",
    "href": "/explainInfo/decisionList.do?menuNo=90010100&upperMenuId=90010000",
    "onclick": "",
    "target": "",
    "has_bbs_id": false,
    "outer_html": "<a href=\"/explainInfo/decisionList.do?menuNo=90010100&amp;upperMenuId=90010000\">법원 판례</a>"
  },
  {
    "index": 15,
    "text": "법제처 유권해석",
    "href": "/explainInfo/lawInterpretationList.do?menuNo=9030000&upperMenuId=9000000",
    "onclick": "",
    "target": "",
    "has_bbs_id": false,
    "outer_html": "<a href=\"/explainInfo/lawInterpretationList.do?menuNo=9030000&amp;upperMenuId=9000000\">법제처 유권해석</a>"
  },
  {
    "index": 16,
    "text": "조세심판원 심판결정례",
    "href": "/explainInfo/judgeDecisionList.do?menuNo=9040000&upperMenuId=9000000",
    "onclick": "",
    "target": "",
    "has_bbs_id": false,
    "outer_html": "<a href=\"/explainInfo/judgeDecisionList.do?menuNo=9040000&amp;upperMenuId=9000000\">조세심판원 심판결정례</a>"
  },
  {
    "index": 17,
    "text": "감사원 심사결정례",
    "href": "/explainInfo/dlbDcnList.do?menuNo=9050000&upperMenuId=9000000",
    "onclick": "",
    "target": "",
    "has_bbs_id": false,
    "outer_html": "<a href=\"/explainInfo/dlbDcnList.do?menuNo=9050000&amp;upperMenuId=9000000\">감사원 심사결정례</a>"
  },
  {
    "index": 18,
    "text": "행정안전부 유권해석",
    "href": "/explainInfo/authoInterpretationList.do?menuNo=9020000&upperMenuId=9000000",
    "onclick": "",
    "target": "",
    "has_bbs_id": false,
    "outer_html": "<a href=\"/explainInfo/authoInterpretationList.do?menuNo=9020000&amp;upperMenuId=9000000\">행정안전부 유권해석</a>"
  },
  {
    "index": 20,
    "text": "전자도서관(E-Book)",
    "href": "/ebook/catalist.do?Dir=0600000000&menuNo=12050500&upperMenuId=12050000&menuNo=12050100&upperMenuId=12050000",
    "onclick": "",
    "target": "",
    "has_bbs_id": false,
    "outer_html": "<a href=\"/ebook/catalist.do?Dir=0600000000&amp;menuNo=12050500&amp;upperMenuId=12050000&amp;menuNo=12050100&amp;upperMenuId=12050000\">전자도서관(E-Book)</a>"
  },
  {
    "index": 21,
    "text": "시가표준액",
    "href": "/cop/bbs/selectBoardList.do?bbsId=BBSMSTR_000000000214&menuNo=12090100&upperMenuId=12090000",
    "onclick": "",
    "target": "",
    "has_bbs_id": true,
    "outer_html": "<a href=\"/cop/bbs/selectBoardList.do?bbsId=BBSMSTR_000000000214&amp;menuNo=12090100&amp;upperMenuId=12090000\">시가표준액</a>"
  },
  {
    "index": 22,
    "text": "온라인교육",
    "href": "/education/selectOnlineEducationList.do?evMenuNo=70100000&menuNo=21110100&upperMenuId=21110000",
    "onclick": "",
    "target": "",
    "has_bbs_id": false,
    "outer_html": "<a href=\"/education/selectOnlineEducationList.do?evMenuNo=70100000&amp;menuNo=21110100&amp;upperMenuId=21110000\">온라인교육</a>"
  },
  {
    "index": 23,
    "text": "참고자료",
    "href": "/cop/bbs/selectBoardList.do?bbsId=BBSMSTR_000000000261&menuNo=12100000&upperMenuId=12000000",
    "onclick": "",
    "target": "",
    "has_bbs_id": true,
    "outer_html": "<a href=\"/cop/bbs/selectBoardList.do?bbsId=BBSMSTR_000000000261&amp;menuNo=12100000&amp;upperMenuId=12000000\">참고자료</a>"
  },
  {
    "index": 24,
    "text": "한국지방세연구원",
    "href": "https://www.kilf.re.kr/?upperMenuId=8500000",
    "onclick": "",
    "target": "",
    "has_bbs_id": false,
    "outer_html": "<a href=\"https://www.kilf.re.kr/?upperMenuId=8500000\" class=\"\">한국지방세연구원</a>"
  },
  {
    "index": 25,
    "text": "한국지방세연구원",
    "href": "https://www.kilf.re.kr/?menuNo=8510000&upperMenuId=8500000",
    "onclick": "",
    "target": "",
    "has_bbs_id": false,
    "outer_html": "<a href=\"https://www.kilf.re.kr/?menuNo=8510000&amp;upperMenuId=8500000\">한국지방세연구원</a>"
  },
  {
    "index": 26,
    "text": "공식채널(지튜브)",
    "href": "https://www.youtube.com/channel/UCCCmppW038WL6aOfky-35lQ?menuNo=8520000&upperMenuId=8500000",
    "onclick": "",
    "target": "",
    "has_bbs_id": false,
    "outer_html": "<a href=\"https://www.youtube.com/channel/UCCCmppW038WL6aOfky-35lQ?menuNo=8520000&amp;upperMenuId=8500000\">공식채널(지튜브)</a>"
  },
  {
    "index": 27,
    "text": "알림마당",
    "href": "/cop/bbs/selectBoardList.do?bbsId=BBSMSTR_000000000011&menuNo=13010000&upperMenuId=13000000",
    "onclick": "",
    "target": "",
    "has_bbs_id": true,
    "outer_html": "<a href=\"/cop/bbs/selectBoardList.do?bbsId=BBSMSTR_000000000011&amp;menuNo=13010000&amp;upperMenuId=13000000\" class=\"\">알림마당</a>"
  },
  {
    "index": 28,
    "text": "공지사항",
    "href": "/cop/bbs/selectBoardList.do?bbsId=BBSMSTR_000000000011&menuNo=13010000&upperMenuId=13000000",
    "onclick": "",
    "target": "",
    "has_bbs_id": true,
    "outer_html": "<a href=\"/cop/bbs/selectBoardList.do?bbsId=BBSMSTR_000000000011&amp;menuNo=13010000&amp;upperMenuId=13000000\">공지사항</a>"
  },
  {
    "index": 29,
    "text": "이용안내 Q&A",
    "href": "/cop/bbs/selectBoardList.do?bbsId=BBSMSTR_000000000081&menuNo=14600000&upperMenuId=13000000",
    "onclick": "",
    "target": "",
    "has_bbs_id": true,
    "outer_html": "<a href=\"/cop/bbs/selectBoardList.do?bbsId=BBSMSTR_000000000081&amp;menuNo=14600000&amp;upperMenuId=13000000\">이용안내 Q&amp;A</a>"
  },
  {
    "index": 30,
    "text": "FAQ",
    "href": "/common/faqView.do?menuNo=13050000&upperMenuId=13000000",
    "onclick": "",
    "target": "",
    "has_bbs_id": true,
    "outer_html": "<a href=\"/common/faqView.do?menuNo=13050000&amp;upperMenuId=13000000\">FAQ</a>"
  },
  {
    "index": 31,
    "text": "쟁송사무",
    "href": "/cop/bbs/selectBoardArticle.do?nttId=26580&bbsId=BBSMSTR_000000000342&menuNo=21270102&upperMenuId=19100000",
    "onclick": "",
    "target": "",
    "has_bbs_id": true,
    "outer_html": "<a href=\"/cop/bbs/selectBoardArticle.do?nttId=26580&amp;bbsId=BBSMSTR_000000000342&amp;menuNo=21270102&amp;upperMenuId=19100000\" class=\"\">쟁송사무</a>"
  },
  {
    "index": 32,
    "text": "자문지원 절차 및 안내",
    "href": "/cop/bbs/selectBoardArticle.do?nttId=26580&bbsId=BBSMSTR_000000000342&menuNo=21270102&upperMenuId=19100000",
    "onclick": "",
    "target": "",
    "has_bbs_id": true,
    "outer_html": "<a href=\"/cop/bbs/selectBoardArticle.do?nttId=26580&amp;bbsId=BBSMSTR_000000000342&amp;menuNo=21270102&amp;upperMenuId=19100000\">자문지원 절차 및 안내</a>"
  },
  {
    "index": 33,
    "text": "쟁송사무지원 사례집(매년)",
    "href": "/cop/bbs/selectBoardList.do?bbsId=BBSMSTR_000000000343&menuNo=21270103&upperMenuId=19100000",
    "onclick": "",
    "target": "",
    "has_bbs_id": true,
    "outer_html": "<a href=\"/cop/bbs/selectBoardList.do?bbsId=BBSMSTR_000000000343&amp;menuNo=21270103&amp;upperMenuId=19100000\">쟁송사무지원 사례집(매년)</a>"
  },
  {
    "index": 34,
    "text": "쟁송사무지원 신청사례 알림방(수시)",
    "href": "/cop/bbs/selectBoardList.do?bbsId=BBSMSTR_000000000371&menuNo=21270106&upperMenuId=19100000",
    "onclick": "",
    "target": "",
    "has_bbs_id": true,
    "outer_html": "<a href=\"/cop/bbs/selectBoardList.do?bbsId=BBSMSTR_000000000371&amp;menuNo=21270106&amp;upperMenuId=19100000\">쟁송사무지원 신청사례 알림방(수시)</a>"
  },
  {
    "index": 35,
    "text": "전국단위사건",
    "href": "/cop/bbs/selectBoardList.do?bbsId=BBSMSTR_000000000361&menuNo=21270100&upperMenuId=21270107",
    "onclick": "",
    "target": "",
    "has_bbs_id": true,
    "outer_html": "<a href=\"/cop/bbs/selectBoardList.do?bbsId=BBSMSTR_000000000361&amp;menuNo=21270100&amp;upperMenuId=21270107\">전국단위사건</a>"
  },
  {
    "index": 36,
    "text": "쟁송사무워크숍 자료",
    "href": "/cop/bbs/selectBoardList.do?bbsId=BBSMSTR_000000000362&menuNo=21270105&upperMenuId=19100000",
    "onclick": "",
    "target": "",
    "has_bbs_id": true,
    "outer_html": "<a href=\"/cop/bbs/selectBoardList.do?bbsId=BBSMSTR_000000000362&amp;menuNo=21270105&amp;upperMenuId=19100000\">쟁송사무워크숍 자료</a>"
  },
  {
    "index": 37,
    "text": "쟁송사무 소통마당",
    "href": "/cop/bbs/selectBoardList.do?bbsId=BBSMSTR_000000000391&menuNo=21270100&upperMenuId=21270109",
    "onclick": "",
    "target": "",
    "has_bbs_id": true,
    "outer_html": "<a href=\"/cop/bbs/selectBoardList.do?bbsId=BBSMSTR_000000000391&amp;menuNo=21270100&amp;upperMenuId=21270109\">쟁송사무 소통마당</a>"
  },
  {
    "index": 38,
    "text": "공무원마당",
    "href": "/cop/bbs/selectNoticeSearchList.do?menuNo=21100000&upperMenuId=21000000",
    "onclick": "",
    "target": "",
    "has_bbs_id": false,
    "outer_html": "<a href=\"/cop/bbs/selectNoticeSearchList.do?menuNo=21100000&amp;upperMenuId=21000000\" class=\"\">공무원마당</a>"
  },
  {
    "index": 40,
    "text": "질의응답",
    "href": "/cop/bbs/selectBoardList.do?bbsId=BBSMSTR_000000000151&menuNo=21200100&upperMenuId=21200000",
    "onclick": "",
    "target": "",
    "has_bbs_id": true,
    "outer_html": "<a href=\"/cop/bbs/selectBoardList.do?bbsId=BBSMSTR_000000000151&amp;menuNo=21200100&amp;upperMenuId=21200000\">질의응답</a>"
  },
  {
    "index": 41,
    "text": "지방세 상담",
    "href": "/cop/bbs/selectBoardList.do?bbsId=BBSMSTR_000000000181&menuNo=21300000&upperMenuId=21000000",
    "onclick": "",
    "target": "",
    "has_bbs_id": true,
    "outer_html": "<a href=\"/cop/bbs/selectBoardList.do?bbsId=BBSMSTR_000000000181&amp;menuNo=21300000&amp;upperMenuId=21000000\">지방세 상담</a>"
  },
  {
    "index": 42,
    "text": "실무자료",
    "href": "/cop/bbs/selectBoardList.do?bbsId=BBSMSTR_000000000221&menuNo=21500100&upperMenuId=21500000",
    "onclick": "",
    "target": "",
    "has_bbs_id": true,
    "outer_html": "<a href=\"/cop/bbs/selectBoardList.do?bbsId=BBSMSTR_000000000221&amp;menuNo=21500100&amp;upperMenuId=21500000\">실무자료</a>"
  },
  {
    "index": 43,
    "text": "자유게시판",
    "href": "/cop/bbs/selectBoardList.do?bbsId=BBSMSTR_000000000211&menuNo=21900000&upperMenuId=21000000",
    "onclick": "",
    "target": "",
    "has_bbs_id": true,
    "outer_html": "<a href=\"/cop/bbs/selectBoardList.do?bbsId=BBSMSTR_000000000211&amp;menuNo=21900000&amp;upperMenuId=21000000\">자유게시판</a>"
  },
  {
    "index": 44,
    "text": "연혁별 개정세법 적용요령",
    "href": "/cop/bbs/selectBoardList.do?bbsId=BBSMSTR_000000000421&menuNo=21600000&upperMenuId=21000000",
    "onclick": "",
    "target": "",
    "has_bbs_id": true,
    "outer_html": "<a href=\"/cop/bbs/selectBoardList.do?bbsId=BBSMSTR_000000000421&amp;menuNo=21600000&amp;upperMenuId=21000000\">연혁별 개정세법 적용요령</a>"
  },
  {
    "index": 45,
    "text": "지방자치단체 소통마당",
    "href": "/cop/bbs/selectLocalMap.do?bbsId=BBSMSTR_100000000001&menuNo=21150000&upperMenuId=21000000",
    "onclick": "",
    "target": "",
    "has_bbs_id": true,
    "outer_html": "<a href=\"/cop/bbs/selectLocalMap.do?bbsId=BBSMSTR_100000000001&amp;menuNo=21150000&amp;upperMenuId=21000000\">지방자치단체 소통마당</a>"
  },
  {
    "index": 46,
    "text": "지방세 관계 법령",
    "href": "/ordinance/importantList.do?menuNo=80100100&upperMenuId=8010000",
    "onclick": "",
    "target": "",
    "has_bbs_id": false,
    "outer_html": "<a href=\"/ordinance/importantList.do?menuNo=80100100&amp;upperMenuId=8010000\">지방세 관계 법령</a>"
  },
  {
    "index": 47,
    "text": "지방자치단체 조례",
    "href": "/ordinance/rulesListAPI.do?menuNo=8020000&upperMenuId=8000000",
    "onclick": "",
    "target": "",
    "has_bbs_id": false,
    "outer_html": "<a href=\"/ordinance/rulesListAPI.do?menuNo=8020000&amp;upperMenuId=8000000\">지방자치단체 조례</a>"
  },
  {
    "index": 48,
    "text": "최신 개정법령",
    "href": "/ordinance/theLastestList.do?menuNo=8030000&upperMenuId=8000000",
    "onclick": "",
    "target": "",
    "has_bbs_id": false,
    "outer_html": "<a href=\"/ordinance/theLastestList.do?menuNo=8030000&amp;upperMenuId=8000000\">최신 개정법령</a>"
  },
  {
    "index": 49,
    "text": "헌법재판소 결정례",
    "href": "/explainInfo/constitutionDcnList.do?menuNo=9060000&upperMenuId=9000000",
    "onclick": "",
    "target": "",
    "has_bbs_id": false,
    "outer_html": "<a href=\"/explainInfo/constitutionDcnList.do?menuNo=9060000&amp;upperMenuId=9000000\">헌법재판소 결정례</a>"
  },
  {
    "index": 50,
    "text": "법원 판례",
    "href": "/explainInfo/decisionList.do?menuNo=90010100&upperMenuId=90010000",
    "onclick": "",
    "target": "",
    "has_bbs_id": false,
    "outer_html": "<a href=\"/explainInfo/decisionList.do?menuNo=90010100&amp;upperMenuId=90010000\">법원 판례</a>"
  },
  {
    "index": 51,
    "text": "법제처 유권해석",
    "href": "/explainInfo/lawInterpretationList.do?menuNo=9030000&upperMenuId=9000000",
    "onclick": "",
    "target": "",
    "has_bbs_id": false,
    "outer_html": "<a href=\"/explainInfo/lawInterpretationList.do?menuNo=9030000&amp;upperMenuId=9000000\">법제처 유권해석</a>"
  },
  {
    "index": 52,
    "text": "조세심판원 심판결정례",
    "href": "/explainInfo/judgeDecisionList.do?menuNo=9040000&upperMenuId=9000000",
    "onclick": "",
    "target": "",
    "has_bbs_id": false,
    "outer_html": "<a href=\"/explainInfo/judgeDecisionList.do?menuNo=9040000&amp;upperMenuId=9000000\">조세심판원 심판결정례</a>"
  },
  {
    "index": 53,
    "text": "감사원 심사결정례",
    "href": "/explainInfo/dlbDcnList.do?menuNo=9050000&upperMenuId=9000000",
    "onclick": "",
    "target": "",
    "has_bbs_id": false,
    "outer_html": "<a href=\"/explainInfo/dlbDcnList.do?menuNo=9050000&amp;upperMenuId=9000000\">감사원 심사결정례</a>"
  },
  {
    "index": 54,
    "text": "행정안전부 유권해석",
    "href": "/explainInfo/authoInterpretationList.do?menuNo=9020000&upperMenuId=9000000",
    "onclick": "",
    "target": "",
    "has_bbs_id": false,
    "outer_html": "<a href=\"/explainInfo/authoInterpretationList.do?menuNo=9020000&amp;upperMenuId=9000000\">행정안전부 유권해석</a>"
  },
  {
    "index": 55,
    "text": "전자도서관(E-Book)",
    "href": "/ebook/catalist.do?Dir=0600000000&menuNo=12050500&upperMenuId=12050000&menuNo=12050100&upperMenuId=12050000",
    "onclick": "",
    "target": "",
    "has_bbs_id": false,
    "outer_html": "<a href=\"/ebook/catalist.do?Dir=0600000000&amp;menuNo=12050500&amp;upperMenuId=12050000&amp;menuNo=12050100&amp;upperMenuId=12050000\">전자도서관(E-Book)</a>"
  },
  {
    "index": 56,
    "text": "시가표준액",
    "href": "/cop/bbs/selectBoardList.do?bbsId=BBSMSTR_000000000214&menuNo=12090100&upperMenuId=12090000",
    "onclick": "",
    "target": "",
    "has_bbs_id": true,
    "outer_html": "<a href=\"/cop/bbs/selectBoardList.do?bbsId=BBSMSTR_000000000214&amp;menuNo=12090100&amp;upperMenuId=12090000\">시가표준액</a>"
  },
  {
    "index": 57,
    "text": "온라인교육",
    "href": "/education/selectOnlineEducationList.do?evMenuNo=70100000&menuNo=21110100&upperMenuId=21110000",
    "onclick": "",
    "target": "",
    "has_bbs_id": false,
    "outer_html": "<a href=\"/education/selectOnlineEducationList.do?evMenuNo=70100000&amp;menuNo=21110100&amp;upperMenuId=21110000\">온라인교육</a>"
  },
  {
    "index": 58,
    "text": "참고자료",
    "href": "/cop/bbs/selectBoardList.do?bbsId=BBSMSTR_000000000261&menuNo=12100000&upperMenuId=12000000",
    "onclick": "",
    "target": "",
    "has_bbs_id": true,
    "outer_html": "<a href=\"/cop/bbs/selectBoardList.do?bbsId=BBSMSTR_000000000261&amp;menuNo=12100000&amp;upperMenuId=12000000\">참고자료</a>"
  },
  {
    "index": 59,
    "text": "한국지방세연구원",
    "href": "https://www.kilf.re.kr/?menuNo=8510000&upperMenuId=8500000",
    "onclick": "",
    "target": "",
    "has_bbs_id": false,
    "outer_html": "<a href=\"https://www.kilf.re.kr/?menuNo=8510000&amp;upperMenuId=8500000\">한국지방세연구원</a>"
  },
  {
    "index": 60,
    "text": "공식채널(지튜브)",
    "href": "https://www.youtube.com/channel/UCCCmppW038WL6aOfky-35lQ?menuNo=8520000&upperMenuId=8500000",
    "onclick": "",
    "target": "",
    "has_bbs_id": false,
    "outer_html": "<a href=\"https://www.youtube.com/channel/UCCCmppW038WL6aOfky-35lQ?menuNo=8520000&amp;upperMenuId=8500000\">공식채널(지튜브)</a>"
  },
  {
    "index": 61,
    "text": "공지사항",
    "href": "/cop/bbs/selectBoardList.do?bbsId=BBSMSTR_000000000011&menuNo=13010000&upperMenuId=13000000",
    "onclick": "",
    "target": "",
    "has_bbs_id": true,
    "outer_html": "<a href=\"/cop/bbs/selectBoardList.do?bbsId=BBSMSTR_000000000011&amp;menuNo=13010000&amp;upperMenuId=13000000\">공지사항</a>"
  },
  {
    "index": 62,
    "text": "이용안내 Q&A",
    "href": "/cop/bbs/selectBoardList.do?bbsId=BBSMSTR_000000000081&menuNo=14600000&upperMenuId=13000000",
    "onclick": "",
    "target": "",
    "has_bbs_id": true,
    "outer_html": "<a href=\"/cop/bbs/selectBoardList.do?bbsId=BBSMSTR_000000000081&amp;menuNo=14600000&amp;upperMenuId=13000000\">이용안내 Q&amp;A</a>"
  },
  {
    "index": 63,
    "text": "FAQ",
    "href": "/common/faqView.do?menuNo=13050000&upperMenuId=13000000",
    "onclick": "",
    "target": "",
    "has_bbs_id": true,
    "outer_html": "<a href=\"/common/faqView.do?menuNo=13050000&amp;upperMenuId=13000000\">FAQ</a>"
  },
  {
    "index": 64,
    "text": "자문지원 절차 및 안내",
    "href": "/cop/bbs/selectBoardArticle.do?nttId=26580&bbsId=BBSMSTR_000000000342&menuNo=21270102&upperMenuId=19100000",
    "onclick": "",
    "target": "",
    "has_bbs_id": true,
    "outer_html": "<a href=\"/cop/bbs/selectBoardArticle.do?nttId=26580&amp;bbsId=BBSMSTR_000000000342&amp;menuNo=21270102&amp;upperMenuId=19100000\">자문지원 절차 및 안내</a>"
  },
  {
    "index": 65,
    "text": "쟁송사무지원 사례집(매년)",
    "href": "/cop/bbs/selectBoardList.do?bbsId=BBSMSTR_000000000343&menuNo=21270103&upperMenuId=19100000",
    "onclick": "",
    "target": "",
    "has_bbs_id": true,
    "outer_html": "<a href=\"/cop/bbs/selectBoardList.do?bbsId=BBSMSTR_000000000343&amp;menuNo=21270103&amp;upperMenuId=19100000\">쟁송사무지원 사례집(매년)</a>"
  },
  {
    "index": 66,
    "text": "쟁송사무지원 신청사례 알림방(수시)",
    "href": "/cop/bbs/selectBoardList.do?bbsId=BBSMSTR_000000000371&menuNo=21270106&upperMenuId=19100000",
    "onclick": "",
    "target": "",
    "has_bbs_id": true,
    "outer_html": "<a href=\"/cop/bbs/selectBoardList.do?bbsId=BBSMSTR_000000000371&amp;menuNo=21270106&amp;upperMenuId=19100000\">쟁송사무지원 신청사례 알림방(수시)</a>"
  },
  {
    "index": 67,
    "text": "전국단위사건",
    "href": "/cop/bbs/selectBoardList.do?bbsId=BBSMSTR_000000000361&menuNo=21270100&upperMenuId=21270107",
    "onclick": "",
    "target": "",
    "has_bbs_id": true,
    "outer_html": "<a href=\"/cop/bbs/selectBoardList.do?bbsId=BBSMSTR_000000000361&amp;menuNo=21270100&amp;upperMenuId=21270107\">전국단위사건</a>"
  },
  {
    "index": 68,
    "text": "쟁송사무워크숍 자료",
    "href": "/cop/bbs/selectBoardList.do?bbsId=BBSMSTR_000000000362&menuNo=21270105&upperMenuId=19100000",
    "onclick": "",
    "target": "",
    "has_bbs_id": true,
    "outer_html": "<a href=\"/cop/bbs/selectBoardList.do?bbsId=BBSMSTR_000000000362&amp;menuNo=21270105&amp;upperMenuId=19100000\">쟁송사무워크숍 자료</a>"
  },
  {
    "index": 69,
    "text": "쟁송사무 소통마당",
    "href": "/cop/bbs/selectBoardList.do?bbsId=BBSMSTR_000000000391&menuNo=21270100&upperMenuId=21270109",
    "onclick": "",
    "target": "",
    "has_bbs_id": true,
    "outer_html": "<a href=\"/cop/bbs/selectBoardList.do?bbsId=BBSMSTR_000000000391&amp;menuNo=21270100&amp;upperMenuId=21270109\">쟁송사무 소통마당</a>"
  },
  {
    "index": 71,
    "text": "질의응답",
    "href": "/cop/bbs/selectBoardList.do?bbsId=BBSMSTR_000000000151&menuNo=21200100&upperMenuId=21200000",
    "onclick": "",
    "target": "",
    "has_bbs_id": true,
    "outer_html": "<a href=\"/cop/bbs/selectBoardList.do?bbsId=BBSMSTR_000000000151&amp;menuNo=21200100&amp;upperMenuId=21200000\">질의응답</a>"
  },
  {
    "index": 72,
    "text": "지방세 상담",
    "href": "/cop/bbs/selectBoardList.do?bbsId=BBSMSTR_000000000181&menuNo=21300000&upperMenuId=21000000",
    "onclick": "",
    "target": "",
    "has_bbs_id": true,
    "outer_html": "<a href=\"/cop/bbs/selectBoardList.do?bbsId=BBSMSTR_000000000181&amp;menuNo=21300000&amp;upperMenuId=21000000\">지방세 상담</a>"
  },
  {
    "index": 73,
    "text": "실무자료",
    "href": "/cop/bbs/selectBoardList.do?bbsId=BBSMSTR_000000000221&menuNo=21500100&upperMenuId=21500000",
    "onclick": "",
    "target": "",
    "has_bbs_id": true,
    "outer_html": "<a href=\"/cop/bbs/selectBoardList.do?bbsId=BBSMSTR_000000000221&amp;menuNo=21500100&amp;upperMenuId=21500000\">실무자료</a>"
  },
  {
    "index": 74,
    "text": "자유게시판",
    "href": "/cop/bbs/selectBoardList.do?bbsId=BBSMSTR_000000000211&menuNo=21900000&upperMenuId=21000000",
    "onclick": "",
    "target": "",
    "has_bbs_id": true,
    "outer_html": "<a href=\"/cop/bbs/selectBoardList.do?bbsId=BBSMSTR_000000000211&amp;menuNo=21900000&amp;upperMenuId=21000000\">자유게시판</a>"
  },
  {
    "index": 75,
    "text": "연혁별 개정세법 적용요령",
    "href": "/cop/bbs/selectBoardList.do?bbsId=BBSMSTR_000000000421&menuNo=21600000&upperMenuId=21000000",
    "onclick": "",
    "target": "",
    "has_bbs_id": true,
    "outer_html": "<a href=\"/cop/bbs/selectBoardList.do?bbsId=BBSMSTR_000000000421&amp;menuNo=21600000&amp;upperMenuId=21000000\">연혁별 개정세법 적용요령</a>"
  },
  {
    "index": 76,
    "text": "지방자치단체 소통마당",
    "href": "/cop/bbs/selectLocalMap.do?bbsId=BBSMSTR_100000000001&menuNo=21150000&upperMenuId=21000000",
    "onclick": "",
    "target": "",
    "has_bbs_id": true,
    "outer_html": "<a href=\"/cop/bbs/selectLocalMap.do?bbsId=BBSMSTR_100000000001&amp;menuNo=21150000&amp;upperMenuId=21000000\">지방자치단체 소통마당</a>"
  },
  {
    "index": 77,
    "text": "내가 본 정보",
    "href": "#search_tab_1",
    "onclick": "",
    "target": "",
    "has_bbs_id": false,
    "outer_html": "<a href=\"#search_tab_1\" class=\"selected\">내가 본 정보</a>"
  },
  {
    "index": 81,
    "text": "보관함 추가",
    "href": "javascript:void(0);",
    "onclick": "",
    "target": "",
    "has_bbs_id": false,
    "outer_html": "<a class=\"sbv_btn01\" id=\"add_cabinet\" href=\"javascript:void(0);\">보관함 추가</a>"
  },
  {
    "index": 83,
    "text": "보관함 변경",
    "href": "javascript:void(0);",
    "onclick": "",
    "target": "",
    "has_bbs_id": false,
    "outer_html": "<a class=\"sbv_btn03\" id=\"edit_cabinet\" href=\"javascript:void(0);\">보관함 변경</a>"
  },
  {
    "index": 96,
    "text": "헌법재판소결정례",
    "href": "javascript:doCollection('ordinance');",
    "onclick": "",
    "target": "",
    "has_bbs_id": false,
    "outer_html": "<a href=\"javascript:doCollection('ordinance');\">헌법재판소<br>결정례</a>"
  },
  {
    "index": 97,
    "text": "법원판례 대법원 하급심",
    "href": "javascript:doCollection('sentencing');",
    "onclick": "",
    "target": "",
    "has_bbs_id": false,
    "outer_html": "<a href=\"javascript:doCollection('sentencing');\" class=\"oneline\">\n\t\t\t\t\t\t<span class=\"top\">법원판례</span>\n\t\t\t\t\t\t<span>대법원</span>\n\t\t\t\t\t\t<span class=\"lower\">하급심</span>\n\t\t\t\t\t</a>"
  },
  {
    "index": 98,
    "text": "조세심판원결정례",
    "href": "javascript:doCollection('screen');",
    "onclick": "",
    "target": "",
    "has_bbs_id": false,
    "outer_html": "<a href=\"javascript:doCollection('screen');\">조세심판원<br>결정례</a>"
  },
  {
    "index": 99,
    "text": "감사원결정례",
    "href": "javascript:doCollection('evaluation');",
    "onclick": "",
    "target": "",
    "has_bbs_id": false,
    "outer_html": "<a href=\"javascript:doCollection('evaluation');\">감사원<br>결정례</a>"
  },
  {
    "index": 100,
    "text": "법제처해석",
    "href": "javascript:doCollection('legal');",
    "onclick": "",
    "target": "",
    "has_bbs_id": false,
    "outer_html": "<a href=\"javascript:doCollection('legal');\" class=\"oneline\">법제처해석</a>"
  },
  {
    "index": 101,
    "text": "행정안전부유권해석",
    "href": "javascript:doCollection('authoritative');",
    "onclick": "",
    "target": "",
    "has_bbs_id": false,
    "outer_html": "<a href=\"javascript:doCollection('authoritative');\">행정안전부<br>유권해석</a>"
  },
  {
    "index": 104,
    "text": "최근 6개월",
    "href": "javascript:SetDate('180');",
    "onclick": "",
    "target": "",
    "has_bbs_id": false,
    "outer_html": "<a href=\"javascript:SetDate('180');\">최근 6개월</a>"
  },
  {
    "index": 105,
    "text": "최근 1년",
    "href": "javascript:SetDate('365');",
    "onclick": "",
    "target": "",
    "has_bbs_id": false,
    "outer_html": "<a href=\"javascript:SetDate('365');\">최근 1년</a>"
  },
  {
    "index": 106,
    "text": "최근 2년",
    "href": "javascript:SetDate('730');",
    "onclick": "",
    "target": "",
    "has_bbs_id": false,
    "outer_html": "<a href=\"javascript:SetDate('730');\">최근 2년</a>"
  },
  {
    "index": 107,
    "text": "최근 3년",
    "href": "javascript:SetDate('1095');",
    "onclick": "",
    "target": "",
    "has_bbs_id": false,
    "outer_html": "<a href=\"javascript:SetDate('1095');\">최근 3년</a>"
  },
  {
    "index": 108,
    "text": "최근 4년",
    "href": "javascript:SetDate('1460');",
    "onclick": "",
    "target": "",
    "has_bbs_id": false,
    "outer_html": "<a href=\"javascript:SetDate('1460');\">최근 4년</a>"
  },
  {
    "index": 109,
    "text": "최근 5년",
    "href": "javascript:SetDate('1825');",
    "onclick": "",
    "target": "",
    "has_bbs_id": false,
    "outer_html": "<a href=\"javascript:SetDate('1825');\">최근 5년</a>"
  },
  {
    "index": 114,
    "text": "개인정보 취급방침",
    "href": "/privatePolicy.do?seq=",
    "onclick": "",
    "target": "",
    "has_bbs_id": false,
    "outer_html": "<a href=\"/privatePolicy.do?seq=\">개인정보 취급방침</a>"
  }
]